MANIFEST.in
requirements.txt
setup.cfg
setup.py
test/test_application.py
test/test_bigquery.py
test/test_billing.py
test/test_decorators.py
test/test_dnsquery.py
test/test_email_security.py
test/test_google_analytics_v4_report_model.py
test/test_httpauth.py
test/test_httpclient.py
test/test_json_dates.py
test/test_jsonapi.py
test/test_login.py
test/test_models.py
test/test_pullqueue.py
test/test_queue.py
test/test_util.py
webapptitude/__init__.py
webapptitude/application.py
webapptitude/bigquery.py
webapptitude/billing.py
webapptitude/decorator.py
webapptitude/dnsquery.py
webapptitude/googleanalytics.py
webapptitude/googleapi.py
webapptitude/gql.py
webapptitude/handlers.py
webapptitude/httpauth.py
webapptitude/httpclient.py
webapptitude/jsonapi.py
webapptitude/jsonkit.py
webapptitude/models.py
webapptitude/oauthkit.py
webapptitude/pullqueue.py
webapptitude/queue.py
webapptitude/session.py
webapptitude/template.py
webapptitude/test.py
webapptitude/testapp.py
webapptitude/testkit.py
webapptitude/util.py
webapptitude/version.py
webapptitude.egg-info/PKG-INFO
webapptitude.egg-info/SOURCES.txt
webapptitude.egg-info/dependency_links.txt
webapptitude.egg-info/entry_points.txt
webapptitude.egg-info/requires.txt
webapptitude.egg-info/top_level.txt
webapptitude.egg-info/zip-safe