Metadata-Version: 1.1
Name: webapptitude
Version: 0.0.10
Summary: A simple extension on webapp2 to accelerate development on Google AppEngine
Home-page: https://gitlab.com/samba/webapptitude
Author: Sam Briesemeister
Author-email: sam.briesemeister+opensource@gmail.com
License: BSD
Download-URL: https://gitlab.com/samba/webapptitude/repository/archive.tar.gz?ref=v0.0.10
Keywords: webapp2 google appengine
Platform: UNKNOWN
